setup.py
ortukov_sh/__init__.py
ortukov_sh/one.py
ortukov_sh/two.py
ortukov_sh.egg-info/PKG-INFO
ortukov_sh.egg-info/SOURCES.txt
ortukov_sh.egg-info/dependency_links.txt
ortukov_sh.egg-info/top_level.txt